pearl/__init__.py
pearl/bayesnet.py
pearl/common.py
pearl/csi.py
pearl/data.py
pearl/hugin.py
pearl/nodes/__init__.py
pearl/nodes/bayesnetnode.py
pearl/nodes/categorical.py
pearl/nodes/continuous.py
pearl/nodes/deterministic.py
pearl/structure/__init__.py
pearl/structure/naivebayes.py
pearl/structure/tree_augmented_nb.py
pearl_pgm-0.2.0.dist-info/WHEEL
pearl_pgm-0.2.0.dist-info/METADATA
pearl_pgm-0.2.0.dist-info/RECORD
